{
  "divisions": {
    "tactical": {
      "name": {
        "de": "CKP Tactical",
        "en": "CKP Tactical"
      },
      "description": {
        "de": "Hochwertige taktische Ausrüstung für Sicherheitskräfte und Spezialeinheiten. Von Schutzwesten bis zur kompletten Einsatzausrüstung.",
        "en": "High-quality tactical equipment for security forces and special units. From protective vests to complete deployment equipment."
      },
      "categories": [
        {
          "id": "body-armor",
          "name": { "de": "Körperschutz", "en": "Body Armor" }
        },
        {
          "id": "tactical-apparel",
          "name": { "de": "Taktische Bekleidung", "en": "Tactical Apparel" }
        },
        {
          "id": "helmets",
          "name": { "de": "Helme", "en": "Helmets" }
        },
        {
          "id": "plate-carriers",
          "name": { "de": "Plattenträger", "en": "Plate Carriers" }
        },
        {
          "id": "gear",
          "name": { "de": "Ausrüstung", "en": "Gear" }
        }
      ]
    },
    "care": {
      "name": {
        "de": "CKP Care",
        "en": "CKP Care"
      },
      "description": {
        "de": "Medizinische Ausrüstung und Schutzkleidung für Rettungsdienste und medizinisches Personal im Einsatz.",
        "en": "Medical equipment and protective clothing for emergency services and medical personnel in the field."
      },
      "categories": [
        {
          "id": "protective-clothing",
          "name": { "de": "Schutzkleidung", "en": "Protective Clothing" }
        },
        {
          "id": "medical-equipment",
          "name": { "de": "Medizinische Ausrüstung", "en": "Medical Equipment" }
        },
        {
          "id": "respiratory-protection",
          "name": { "de": "Atemschutz", "en": "Respiratory Protection" }
        }
      ]
    }
  },
  "products": [
    {
      "id": "defender-x-gen3",
      "sku": "DEF-X-G3",
      "division": "tactical",
      "name": {
        "de": "Defender-X Gen 3",
        "en": "Defender-X Gen 3"
      },
      "category": "body-armor",
      "tags": {
        "de": ["Körperschutz"],
        "en": ["Body Armor"]
      },
      "badge": {
        "de": "BESTSELLER",
        "en": "BESTSELLER"
      },
      "description": {
        "de": "Verdeckter ballistischer Schutz für professionelle Einsätze. Leicht, diskret und höchster Schutzstandard.",
        "en": "Covert ballistic protection for professional operations. Lightweight, discreet and highest protection standard."
      },
      "specs": {
        "de": ["SK1", "Verdeckt", "Multi-Hit Fähig"],
        "en": ["SK1", "Covert", "Multi-Hit Capable"]
      },
      "features": {
        "de": [
          "Ballistischer Schutz SK1",
          "Verdecktes Design",
          "Multi-Hit zertifiziert",
          "Atmungsaktives Material"
        ],
        "en": [
          "Ballistic Protection SK1",
          "Covert Design",
          "Multi-Hit Certified",
          "Breathable Material"
        ]
      },
      "price": "Auf Anfrage",
      "imageURL": "https://via.placeholder.com/400x400/1a1a1a/ff6b35?text=Defender-X+Gen+3",
      "bestseller": true
    },
    {
      "id": "varan-elite-suit",
      "sku": "VAR-ELI-001",
      "division": "tactical",
      "name": {
        "de": "Varan-Elite Kampfanzug",
        "en": "Varan-Elite Combat Suit"
      },
      "category": "tactical-apparel",
      "tags": {
        "de": ["Taktische Bekleidung"],
        "en": ["Tactical Apparel"]
      },
      "badge": {
        "de": "NEU",
        "en": "NEW ARRIVALS"
      },
      "description": {
        "de": "Multi-Terrain Camouflage Kampfanzug für alle Einsatzbereiche. Robust, flexibel und wetterbeständig.",
        "en": "Multi-terrain camouflage combat suit for all deployment areas. Robust, flexible and weather resistant."
      },
      "specs": {
        "de": ["Multi-Terrain", "Ripstop", "Wasserfest"],
        "en": ["Multi-Terrain", "Ripstop", "Waterproof"]
      },
      "features": {
        "de": [
          "Multi-Terrain Camouflage",
          "Ripstop-Gewebe",
          "Verstärkte Knie/Ellbogen",
          "Integrierte Taschen"
        ],
        "en": [
          "Multi-Terrain Camouflage",
          "Ripstop Fabric",
          "Reinforced Knees/Elbows",
          "Integrated Pockets"
        ]
      },
      "price": "Auf Anfrage",
      "imageURL": "https://via.placeholder.com/400x400/1a1a1a/ff8c42?text=Varan+Elite",
      "bestseller": false
    },
    {
      "id": "sentinel-ops-helmet",
      "sku": "SEN-OPS-H1",
      "division": "tactical",
      "name": {
        "de": "Sentinel Ops Helm",
        "en": "Sentinel Ops Helmet"
      },
      "category": "helmets",
      "tags": {
        "de": ["Helme"],
        "en": ["Helmets"]
      },
      "badge": {
        "de": "PROFESSIONAL",
        "en": "PROFESSIONAL"
      },
      "description": {
        "de": "Level 4 ballistischer Helm mit NVG-Halterung. Maximaler Schutz für Spezialeinheiten.",
        "en": "Level 4 ballistic helmet with NVG mount. Maximum protection for special units."
      },
      "specs": {
        "de": ["Level 4", "NVG Mount", "Multi-Hit"],
        "en": ["Level 4", "NVG Mount", "Multi-Hit"]
      },
      "features": {
        "de": [
          "NIJ Level IIIA",
          "NVG-Halterung",
          "Schienensystem",
          "Komfort-Polsterung"
        ],
        "en": [
          "NIJ Level IIIA",
          "NVG Mount",
          "Rail System",
          "Comfort Padding"
        ]
      },
      "price": "Auf Anfrage",
      "imageURL": "https://via.placeholder.com/400x400/1a1a1a/ff6b35?text=Sentinel+Helmet",
      "bestseller": false
    },
    {
      "id": "guardian-plate-carrier",
      "sku": "GUA-PC-001",
      "division": "tactical",
      "name": {
        "de": "Guardian Plattenträger",
        "en": "Guardian Plate Carrier"
      },
      "category": "plate-carriers",
      "tags": {
        "de": ["Plattenträger"],
        "en": ["Plate Carriers"]
      },
      "badge": null,
      "description": {
        "de": "Modularer Plattenträger für maximale Flexibilität. NIJ IV Schutz mit MOLLE-System.",
        "en": "Modular plate carrier for maximum flexibility. NIJ IV protection with MOLLE system."
      },
      "specs": {
        "de": ["NIJ IV", "Modular", "Cummerbund"],
        "en": ["NIJ IV", "Modular", "Cummerbund"]
      },
      "features": {
        "de": [
          "NIJ IV Zertifiziert",
          "Modulares MOLLE-System",
          "Verstellbarer Cummerbund",
          "Schnellverschluss"
        ],
        "en": [
          "NIJ IV Certified",
          "Modular MOLLE System",
          "Adjustable Cummerbund",
          "Quick Release"
        ]
      },
      "price": "€899.00",
      "imageURL": "https://via.placeholder.com/400x400/1a1a1a/ff6b35?text=Guardian+PC",
      "bestseller": false
    },
    {
      "id": "stealth-ops-backpack",
      "sku": "STE-BAC-001",
      "division": "tactical",
      "name": {
        "de": "Stealth Ops Rucksack",
        "en": "Stealth Ops Backpack"
      },
      "category": "gear",
      "tags": {
        "de": ["Ausrüstung"],
        "en": ["Gear"]
      },
      "badge": null,
      "description": {
        "de": "Low-Profile taktischer Rucksack mit 40L Volumen. MOLLE-kompatibel und Hydration-ready.",
        "en": "Low-profile tactical backpack with 40L volume. MOLLE compatible and hydration ready."
      },
      "specs": {
        "de": ["40L", "MOLLE", "Hydration"],
        "en": ["40L", "MOLLE", "Hydration"]
      },
      "features": {
        "de": [
          "40 Liter Volumen",
          "MOLLE-Webbing",
          "Hydration-System ready",
          "Gepolsterte Träger"
        ],
        "en": [
          "40 Liter Volume",
          "MOLLE Webbing",
          "Hydration System Ready",
          "Padded Straps"
        ]
      },
      "price": "€249.00",
      "imageURL": "https://via.placeholder.com/400x400/1a1a1a/ff8c42?text=Stealth+Backpack",
      "bestseller": false
    },
    {
      "id": "tactical-gloves-pro",
      "sku": "TAC-GLV-P1",
      "division": "tactical",
      "name": {
        "de": "Taktische Handschuhe Pro",
        "en": "Tactical Gloves Pro"
      },
      "category": "gear",
      "tags": {
        "de": ["Ausrüstung"],
        "en": ["Gear"]
      },
      "badge": null,
      "description": {
        "de": "Schnittfeste taktische Handschuhe mit Touchscreen-Kompatibilität. Perfekt für Präzisionsarbeit.",
        "en": "Cut-resistant tactical gloves with touchscreen compatibility. Perfect for precision work."
      },
      "specs": {
        "de": ["Schnittfest", "Touchscreen", "Verstärkt"],
        "en": ["Cut-Resistant", "Touchscreen", "Reinforced"]
      },
      "features": {
        "de": [
          "Schnittfestes Material",
          "Touchscreen-kompatibel",
          "Verstärkte Knöchel",
          "Atmungsaktiv"
        ],
        "en": [
          "Cut-Resistant Material",
          "Touchscreen Compatible",
          "Reinforced Knuckles",
          "Breathable"
        ]
      },
      "price": "€79.00",
      "imageURL": "https://via.placeholder.com/400x400/1a1a1a/ff6b35?text=Tactical+Gloves",
      "bestseller": false
    }
  ]
}